hackedit_cobol/__init__.py
hackedit_cobol/pyqode_cobol_server.py
hackedit_cobol/forms/__init__.py
hackedit_cobol/forms/dlg_check_compiler_ui.py
hackedit_cobol/forms/dlg_configure_project_ui.py
hackedit_cobol/forms/dlg_dbpre_ui.py
hackedit_cobol/forms/dlg_monospace_output_ui.py
hackedit_cobol/forms/dlg_secondary_compilers_ui.py
hackedit_cobol/forms/hackedit_cobol_rc.py
hackedit_cobol/forms/preferences_editor_ui.py
hackedit_cobol/forms/settings_page_compiler_ui.py
hackedit_cobol/forms/settings_page_preparsers_ui.py
hackedit_cobol/lib/__init__.py
hackedit_cobol/lib/build_thread.py
hackedit_cobol/lib/compiler.py
hackedit_cobol/lib/dbpre.py
hackedit_cobol/lib/dlg_check_compiler.py
hackedit_cobol/lib/dlg_configure.py
hackedit_cobol/lib/esql.py
hackedit_cobol/lib/events.py
hackedit_cobol/lib/linter.py
hackedit_cobol/lib/manager_plugin_base.py
hackedit_cobol/lib/msvc.py
hackedit_cobol/lib/preparsers.py
hackedit_cobol/lib/utils.py
hackedit_cobol/plugins/__init__.py
hackedit_cobol/plugins/compiler_preferences.py
hackedit_cobol/plugins/editor.py
hackedit_cobol/plugins/file_mode.py
hackedit_cobol/plugins/icon_provider.py
hackedit_cobol/plugins/index.py
hackedit_cobol/plugins/indicators.py
hackedit_cobol/plugins/offset.py
hackedit_cobol/plugins/preparsers_preferences.py
hackedit_cobol/plugins/project_mode.py
hackedit_cobol/plugins/templates.py
hackedit_cobol/plugins/workspaces.py
hackedit_cobol/templates/cobol-file-fixed/@fn@.@ext@
hackedit_cobol/templates/cobol-file-fixed/template.json
hackedit_cobol/templates/cobol-file-free/@fn@.@ext@
hackedit_cobol/templates/cobol-file-free/template.json
hackedit_cobol/templates/cobol-project-fixed/main.cbl
hackedit_cobol/templates/cobol-project-fixed/template.json
hackedit_cobol/templates/cobol-project-fixed/.hackedit/config.usr
hackedit_cobol/templates/cobol-project-fixed/.hackedit/project.json
hackedit_cobol/templates/cobol-project-free/main.cbl
hackedit_cobol-1.0a2.dist-info/DESCRIPTION.rst
hackedit_cobol-1.0a2.dist-info/METADATA
hackedit_cobol-1.0a2.dist-info/RECORD
hackedit_cobol-1.0a2.dist-info/WHEEL
hackedit_cobol-1.0a2.dist-info/entry_points.txt
hackedit_cobol-1.0a2.dist-info/metadata.json
hackedit_cobol-1.0a2.dist-info/top_level.txt
